hexagonal/__init__.py
hexagonal/domain/__init__.py
hexagonal/domain/hexagonal_error.py
hexagonal/domain/hexagonal_layer.py
hexagonal/domain/hexagonal_project/__init__.py
hexagonal/domain/hexagonal_project/hexagonal_project.py
hexagonal/domain/hexagonal_project/hexagonal_project_layer.py
hexagonal/domain/python_file.py
hexagonal/domain/python_module.py
hexagonal/domain/raw_python_file.py
hexagonal/hexagonal_config.py
hexagonal/infrastructure/__init__.py
hexagonal/infrastructure/cli.py
hexagonal/services/__init__.py
hexagonal/services/hexagonal_composition.py
hexagonal/services/hexagonal_dependency_flow_checker.py
hexagonal/services/hexagonal_project_builder.py
hexagonal/services/python_file_builder.py
hexagonal/services/python_file_imports_resolver.py
hexagonal/services/raw_python_file_builder.py
hexagonal/services/raw_python_project_importer.py
hexagonal/use_cases/__init__.py
hexagonal/use_cases/check_project_sanity_usecase.py
hexagonal/use_cases/generate_diagram_usecase.py
hexagonal_sanity_check-0.0.21.dist-info/entry_points.txt
hexagonal_sanity_check-0.0.21.dist-info/LICENSE
hexagonal_sanity_check-0.0.21.dist-info/WHEEL
hexagonal_sanity_check-0.0.21.dist-info/METADATA
hexagonal_sanity_check-0.0.21.dist-info/RECORD
