Metadata-Version: 2.1
Name: hexagonal-sanity-check
Version: 0.0.21
Summary: Hexagonal Sanity Check
Keywords: hexagonal architecture,onion architecture,enforce rules
Author: rfrezino
Author-email: rodrigofrezino@gmail.com
Requires-Python: >=3.7,<4.0
Classifier: Programming Language :: Python :: 3
Classifier: Programming Language :: Python :: 3.10
Classifier: Programming Language :: Python :: 3.7
Classifier: Programming Language :: Python :: 3.8
Classifier: Programming Language :: Python :: 3.9
Requires-Dist: click (>=8.0.3,<9.0.0)
Requires-Dist: diagrams (>=0.20.0,<0.21.0)
